fingerprinter/__init__.py
fingerprinter/build.sh
fingerprinter/build_arg_resolver.py
fingerprinter/cli.py
fingerprinter/command_builder.py
fingerprinter/deployment.dockerfile
fingerprinter/fingerprinter.py
fingerprinter/models.py
fingerprinter/target_resolver.py
uw_it_build_fingerprinter-0.2.9.dist-info/entry_points.txt
uw_it_build_fingerprinter-0.2.9.dist-info/LICENSE
uw_it_build_fingerprinter-0.2.9.dist-info/WHEEL
uw_it_build_fingerprinter-0.2.9.dist-info/METADATA
uw_it_build_fingerprinter-0.2.9.dist-info/RECORD
