Metadata-Version: 2.1
Name: uw-it-build-fingerprinter
Version: 0.2.9
Summary: 
Author: Tom Thorogood
Author-email: tom@tomthorogood.com
Requires-Python: >=3.8
Classifier: Programming Language :: Python :: 3
Classifier: Programming Language :: Python :: 3.10
Classifier: Programming Language :: Python :: 3.8
Classifier: Programming Language :: Python :: 3.9
Requires-Dist: PyYAML (>=6.0,<7.0)
Requires-Dist: pydantic (>=1.9.0,<2.0.0)
